fir_4_tap_hardware_share.v
// fir_4_tap_hardware_share.v

// NAMA : WILLIAM ANTHONY
// NIM  : 13223048

module fir_4_tap_hardware_share #(
    parameter DATA_WIDTH = 16,
    parameter COEFF_WIDTH = 16,
    parameter COEFF_FRACTION_WIDTH = 15 // Untuk representasi Q1.15
) (
    input wire clk,
    input wire reset,
    input wire signed [DATA_WIDTH-1:0] i_data,
    input wire i_data_valid, // Sinyal validasi untuk input data
    output wire signed [DATA_WIDTH + COEFF_WIDTH - COEFF_FRACTION_WIDTH + 1:0] o_data_sum, // Lebar output untuk mencegah overflow
    output wire o_data_valid
);

    // Koefisien filter (contoh, Anda bisa mengubahnya sesuai kebutuhan)
    // Untuk representasi Q1.15, 0.5 = 16'h4000, 0.25 = 16'h2000
    // Menggunakan localparam terpisah karena array literal tidak didukung secara universal untuk localparam di Icarus Verilog
    localparam signed [COEFF_WIDTH-1:0] H0_VAL = 16'h1000; // h0 = 0.125
    localparam signed [COEFF_WIDTH-1:0] H1_VAL = 16'h2000; // h1 = 0.25
    localparam signed [COEFF_WIDTH-1:0] H2_VAL = 16'h2000; // h2 = 0.25
    localparam signed [COEFF_WIDTH-1:0] H3_VAL = 16'h1000; // h3 = 0.125

    // FSM States (menggunakan localparam untuk kompatibilitas Verilog murni)
    localparam [2:0]
        IDLE         = 3'b000,
        LOAD_INPUT   = 3'b001,
        MAC_0        = 3'b010,
        MAC_1        = 3'b011,
        MAC_2        = 3'b100,
        MAC_3        = 3'b101,
        OUTPUT_READY = 3'b110;

    reg [2:0] current_state, next_state; // Menggunakan reg untuk state

    // Register untuk menunda input
    reg signed [DATA_WIDTH-1:0] data_reg [0:3]; // x(n), x(n-1), x(n-2), x(n-3)

    // Accumulator untuk menyimpan hasil penjumlahan parsial
    reg signed [DATA_WIDTH + COEFF_WIDTH - COEFF_FRACTION_WIDTH + 1:0] accumulator_reg;

    // Sinyal untuk memilih input data dan koefisien untuk MAC unit
    wire signed [DATA_WIDTH-1:0] mac_data_in;
    wire signed [COEFF_WIDTH-1:0] mac_coeff_in;

    // Output dari MAC unit (perkalian)
    wire signed [DATA_WIDTH + COEFF_WIDTH -1:0] mac_mul_out; // Lebar penuh hasil perkalian sebelum fractional shift

    // Register untuk validasi data output
    reg data_valid_reg_int; // Internal register untuk validasi data

    assign o_data_sum = accumulator_reg;
    assign o_data_valid = data_valid_reg_int;

    // FSM State Register
    always @(posedge clk or posedge reset) begin
        if (reset) begin
            current_state <= IDLE;
        end else begin
            current_state <= next_state;
        end
    end

    // FSM Next State Logic
    always @(*) begin // Menggunakan always @(*) untuk combinational logic
        next_state = current_state; // Default ke current state
        data_valid_reg_int = 1'b0; // Default output valid low

        case (current_state)
            IDLE: begin
                if (i_data_valid) // Hanya transisi jika ada input valid baru
                    next_state = LOAD_INPUT;
            end
            LOAD_INPUT: begin
                next_state = MAC_0;
            end
            MAC_0: begin
                next_state = MAC_1;
            end
            MAC_1: begin
                next_state = MAC_2;
            end
            MAC_2: begin
                next_state = MAC_3;
            end
            MAC_3: begin
                next_state = OUTPUT_READY;
            end
            OUTPUT_READY: begin
                data_valid_reg_int = 1'b1; // Output valid
                // Kembali ke IDLE atau LOAD_INPUT jika ada input baru
                if (i_data_valid)
                    next_state = LOAD_INPUT;
                else
                    next_state = IDLE;
            end
            default: next_state = IDLE;
        endcase
    end

    // Register input data dan accumulator logic
    always @(posedge clk or posedge reset) begin
        if (reset) begin
            data_reg[0] <= 'd0;
            data_reg[1] <= 'd0;
            data_reg[2] <= 'd0;
            data_reg[3] <= 'd0;
            accumulator_reg <= 'd0;
        end else begin
            case (current_state)
                IDLE: begin
                    accumulator_reg <= 'd0; // Reset accumulator saat IDLE
                end
                LOAD_INPUT: begin
                    data_reg[3] <= data_reg[2];
                    data_reg[2] <= data_reg[1];
                    data_reg[1] <= data_reg[0];
                    data_reg[0] <= i_data; // Muat input baru
                end
                MAC_0: begin
                    accumulator_reg <= (mac_mul_out >>> COEFF_FRACTION_WIDTH);
                end
                MAC_1: begin
                    accumulator_reg <= accumulator_reg + (mac_mul_out >>> COEFF_FRACTION_WIDTH);
                end
                MAC_2: begin
                    accumulator_reg <= accumulator_reg + (mac_mul_out >>> COEFF_FRACTION_WIDTH);
                end
                MAC_3: begin
                    accumulator_reg <= accumulator_reg + (mac_mul_out >>> COEFF_FRACTION_WIDTH);
                end
                default: begin
                    // No change
                end
            endcase
        end
    end

    // Multiplexer untuk memilih input data ke MAC unit
    assign mac_data_in = (current_state == MAC_0) ? data_reg[0] :
                         (current_state == MAC_1) ? data_reg[1] :
                         (current_state == MAC_2) ? data_reg[2] :
                         (current_state == MAC_3) ? data_reg[3] : 'd0;

    // Multiplexer untuk memilih koefisien ke MAC unit
    // Menggunakan localparam Hx_VAL yang terpisah
    assign mac_coeff_in = (current_state == MAC_0) ? H0_VAL :
                          (current_state == MAC_1) ? H1_VAL :
                          (current_state == MAC_2) ? H2_VAL :
                          (current_state == MAC_3) ? H3_VAL : 'd0;

    // MAC unit (single multiplier)
    assign mac_mul_out = mac_data_in * mac_coeff_in;

endmodule


// cd D:\FIR_Filter
// iverilog -o fir_hardware_share.vvp fir_4_tap_hardware_share.v tb_fir_hardware_share.v
// vvp fir_hardware_share.vvp
// gtkwave fir_hardware_share.vcd

tb_fir_hardware_share.v
// tb_fir_hardware_share.v
`timescale 1ns / 1ps

module tb_fir_hardware_share;

    // Parameters
    parameter DATA_WIDTH = 16;
    parameter COEFF_WIDTH = 16;
    parameter COEFF_FRACTION_WIDTH = 15; // Q1.15 for coefficients

    // Signals
    reg clk;
    reg reset;
    reg signed [DATA_WIDTH-1:0] i_data;
    reg i_data_valid; // Input valid signal
    wire signed [DATA_WIDTH + COEFF_WIDTH - COEFF_FRACTION_WIDTH + 1:0] o_data_sum;
    wire o_data_valid;

    // Clock Generation
    always #5 clk = ~clk; // 10ns period (100 MHz)

    // DUT Instantiation
    fir_4_tap_hardware_share #(
        .DATA_WIDTH(DATA_WIDTH),
        .COEFF_WIDTH(COEFF_WIDTH),
        .COEFF_FRACTION_WIDTH(COEFF_FRACTION_WIDTH)
    ) dut (
        .clk(clk),
        .reset(reset),
        .i_data(i_data),
        .i_data_valid(i_data_valid),
        .o_data_sum(o_data_sum),
        .o_data_valid(o_data_valid)
    );

    // Initial Block
    initial begin
        // Initialize signals
        clk = 1'b0;
        reset = 1'b1;
        i_data = 'd0;
        i_data_valid = 1'b0;

        // Dump waves for GTKWave
        $dumpfile("fir_hardware_share.vcd");
        $dumpvars(0, tb_fir_hardware_share);

        // Apply reset
        #10 reset = 1'b0;

        // Test vectors for hardware share (requires multiple clock cycles per output)
        // h0=0.125, h1=0.25, h2=0.25, h3=0.125

        // Cycle 0: IDLE
        #10; // First cycle after reset

        // Cycle 1: Input 100
        // State: IDLE -> LOAD_INPUT
        i_data = 16'd100;
        i_data_valid = 1'b1;
        #10; // clk edge, state becomes LOAD_INPUT

        // Cycle 2: MAC_0
        i_data_valid = 1'b0; // Input is processed, deassert valid for next cycle
        #10; // clk edge, state becomes MAC_0

        // Cycle 3: MAC_1
        #10; // clk edge, state becomes MAC_1

        // Cycle 4: MAC_2
        #10; // clk edge, state becomes MAC_2

        // Cycle 5: MAC_3
        #10; // clk edge, state becomes MAC_3

        // Cycle 6: OUTPUT_READY - Output for i_data=100 should be ready (Expected: 12)
        #10; // clk edge, state becomes OUTPUT_READY
        // At this point, o_data_sum should be 12.
        // It's the first actual output that has processed all taps.

        // Cycle 7: Input 200
        // State: OUTPUT_READY -> LOAD_INPUT
        i_data = 16'd200;
        i_data_valid = 1'b1;
        #10; // clk edge, state becomes LOAD_INPUT

        // Cycle 8: MAC_0
        i_data_valid = 1'b0;
        #10; // clk edge, state becomes MAC_0

        // Cycle 9: MAC_1
        #10; // clk edge, state becomes MAC_1

        // Cycle 10: MAC_2
        #10; // clk edge, state becomes MAC_2

        // Cycle 11: MAC_3
        #10; // clk edge, state becomes MAC_3

        // Cycle 12: OUTPUT_READY - Output for i_data=200 should be ready (Expected: 50)
        #10; // clk edge, state becomes OUTPUT_READY
        // At this point, o_data_sum should be 50.

        // Cycle 13: Input 300
        // State: OUTPUT_READY -> LOAD_INPUT
        i_data = 16'd300;
        i_data_valid = 1'b1;
        #10; // clk edge, state becomes LOAD_INPUT

        // Cycle 14: MAC_0
        i_data_valid = 1'b0;
        #10; // clk edge, state becomes MAC_0

        // Cycle 15: MAC_1
        #10; // clk edge, state becomes MAC_1

        // Cycle 16: MAC_2
        #10; // clk edge, state becomes MAC_2

        // Cycle 17: MAC_3
        #10; // clk edge, state becomes MAC_3

        // Cycle 18: OUTPUT_READY - Output for i_data=300 should be ready (Expected: 112)
        #10; // clk edge, state becomes OUTPUT_READY
        // At this point, o_data_sum should be 112.

        // Cycle 19: Input 400
        // State: OUTPUT_READY -> LOAD_INPUT
        i_data = 16'd400;
        i_data_valid = 1'b1;
        #10; // clk edge, state becomes LOAD_INPUT

        // Cycle 20: MAC_0
        i_data_valid = 1'b0;
        #10; // clk edge, state becomes MAC_0

        // Cycle 21: MAC_1
        #10; // clk edge, state becomes MAC_1

        // Cycle 22: MAC_2
        #10; // clk edge, state becomes MAC_2

        // Cycle 23: MAC_3
        #10; // clk edge, state becomes MAC_3

        // Cycle 24: OUTPUT_READY - Output for i_data=400 should be ready (Expected: 187)
        #10; // clk edge, state becomes OUTPUT_READY
        // At this point, o_data_sum should be 187.

        #50 $finish;
    end

    // Monitor outputs
    always @(posedge clk) begin
        if (o_data_valid) begin
            $display("Time: %0t, Input data for this output cycle (i_data when LOAD_INPUT state): %0d, Output: %0d", $time, dut.data_reg[0], o_data_sum);
        end
    end

endmodule

fir_hardware_share.vcd
$date
	Mon Oct 20 10:16:30 2025
$end
$version
	Icarus Verilog
$end
$timescale
	1ps
$end
$scope module tb_fir_hardware_share $end
$var wire 1 ! o_data_valid $end
$var wire 19 " o_data_sum [18:0] $end
$var parameter 32 # COEFF_FRACTION_WIDTH $end
$var parameter 32 $ COEFF_WIDTH $end
$var parameter 32 % DATA_WIDTH $end
$var reg 1 & clk $end
$var reg 16 ' i_data [15:0] $end
$var reg 1 ( i_data_valid $end
$var reg 1 ) reset $end
$scope module dut $end
$var wire 1 & clk $end
$var wire 16 * i_data [15:0] $end
$var wire 1 ( i_data_valid $end
$var wire 19 + o_data_sum [18:0] $end
$var wire 1 ! o_data_valid $end
$var wire 1 ) reset $end
$var wire 32 , mac_mul_out [31:0] $end
$var wire 16 - mac_data_in [15:0] $end
$var wire 16 . mac_coeff_in [15:0] $end
$var parameter 32 / COEFF_FRACTION_WIDTH $end
$var parameter 32 0 COEFF_WIDTH $end
$var parameter 32 1 DATA_WIDTH $end
$var parameter 16 2 H0_VAL $end
$var parameter 16 3 H1_VAL $end
$var parameter 16 4 H2_VAL $end
$var parameter 16 5 H3_VAL $end
$var parameter 3 6 IDLE $end
$var parameter 3 7 LOAD_INPUT $end
$var parameter 3 8 MAC_0 $end
$var parameter 3 9 MAC_1 $end
$var parameter 3 : MAC_2 $end
$var parameter 3 ; MAC_3 $end
$var parameter 3 < OUTPUT_READY $end
$var reg 19 = accumulator_reg [18:0] $end
$var reg 3 > current_state [2:0] $end
$var reg 1 ? data_valid_reg_int $end
$var reg 3 @ next_state [2:0] $end
$upscope $end
$upscope $end
$enddefinitions $end
$comment Show the parameter values. $end
$dumpall
b110 <
b101 ;
b100 :
b11 9
b10 8
b1 7
b0 6
b1000000000000 5
b10000000000000 4
b10000000000000 3
b1000000000000 2
b10000 1
b10000 0
b1111 /
b10000 %
b10000 $
b1111 #
$end
#0
$dumpvars
b0 @
0?
b0 >
b0 =
b0 .
b0 -
b0 ,
b0 +
b0 *
1)
0(
b0 '
0&
b0 "
0!
$end
#5000
1&
#10000
0&
0)
#15000
1&
#20000
b1 @
0&
1(
b1100100 '
b1100100 *
#25000
b10 @
b1 >
1&
#30000
b10 @
0&
0(
#35000
b11 @
b1100100000000000000 ,
b1100100 -
b1000000000000 .
b10 >
1&
#40000
0&
#45000
b100 @
b0 -
b0 ,
b10000000000000 .
b1100 "
b1100 +
b1100 =
b11 >
1&
#50000
0&
#55000
b101 @
b100 >
1&
#60000
0&
#65000
b1000000000000 .
b110 @
b101 >
1&
#70000
0&
#75000
b0 .
b0 @
1!
1?
b110 >
1&
#80000
1!
1?
b1 @
0&
1(
b11001000 '
b11001000 *
#85000
b10 @
0!
0?
b1 >
1&
#90000
b10 @
0&
0(
#95000
b11 @
b11001000000000000000 ,
b11001000 -
b1000000000000 .
b10 >
1&
#100000
0&
#105000
b100 @
b1100100 -
b11001000000000000000 ,
b10000000000000 .
b11001 "
b11001 +
b11001 =
b11 >
1&
#110000
0&
#115000
b0 ,
b0 -
b101 @
b100 >
b110010 "
b110010 +
b110010 =
1&
#120000
0&
#125000
b1000000000000 .
b110 @
b101 >
1&
#130000
0&
#135000
b0 .
b0 @
1!
1?
b110 >
1&
#140000
1!
1?
b1 @
0&
1(
b100101100 '
b100101100 *
#145000
b10 @
0!
0?
b1 >
1&
#150000
b10 @
0&
0(
#155000
b11 @
b100101100000000000000 ,
b100101100 -
b1000000000000 .
b10 >
1&
#160000
0&
#165000
b100 @
b11001000 -
b110010000000000000000 ,
b10000000000000 .
b100101 "
b100101 +
b100101 =
b11 >
1&
#170000
0&
#175000
b11001000000000000000 ,
b1100100 -
b101 @
b100 >
b1010111 "
b1010111 +
b1010111 =
1&
#180000
0&
#185000
b0 -
b0 ,
b1000000000000 .
b110 @
b1110000 "
b1110000 +
b1110000 =
b101 >
1&
#190000
0&
#195000
b0 .
b0 @
1!
1?
b110 >
1&
#200000
1!
1?
b1 @
0&
1(
b110010000 '
b110010000 *
#205000
b10 @
0!
0?
b1 >
1&
#210000
b10 @
0&
0(
#215000
b11 @
b110010000000000000000 ,
b110010000 -
b1000000000000 .
b10 >
1&
#220000
0&
#225000
b100 @
b100101100 -
b1001011000000000000000 ,
b10000000000000 .
b110010 "
b110010 +
b110010 =
b11 >
1&
#230000
0&
#235000
b110010000000000000000 ,
b11001000 -
b101 @
b100 >
b1111101 "
b1111101 +
b1111101 =
1&
#240000
0&
#245000
b1100100 -
b1100100000000000000 ,
b1000000000000 .
b110 @
b10101111 "
b10101111 +
b10101111 =
b101 >
1&
#250000
0&
#255000
b0 -
b0 ,
b0 .
b0 @
1!
1?
b110 >
b10111011 "
b10111011 +
b10111011 =
1&
#260000
0&
#265000
0!
0?
b0 >
1&
#270000
0&
#275000
b0 "
b0 +
b0 =
1&
