fir_4_tap_direct_form.v
// fir_4_tap_direct_form.

// NAMA : WILLIAM ANTHONY
// NIM  : 13223048


module fir_4_tap_direct_form #(
    parameter DATA_WIDTH = 16,
    parameter COEFF_WIDTH = 16,
    parameter COEFF_FRACTION_WIDTH = 15 // Untuk representasi Q1.15
) (
    input wire clk,
    input wire reset,
    input wire signed [DATA_WIDTH-1:0] i_data,
    output wire signed [DATA_WIDTH + COEFF_WIDTH - COEFF_FRACTION_WIDTH + 1:0] o_data_sum, // Lebar output untuk mencegah overflow
    output wire o_data_valid
);

    // Koefisien filter (contoh, Anda bisa mengubahnya sesuai kebutuhan)
    // Untuk representasi Q1.15, 0.5 = 16'h4000, 0.25 = 16'h2000
    // Pastikan koefisien adalah signed
    localparam signed [COEFF_WIDTH-1:0] H0 = 16'h1000; // Contoh: 0.125
    localparam signed [COEFF_WIDTH-1:0] H1 = 16'h2000; // Contoh: 0.25
    localparam signed [COEFF_WIDTH-1:0] H2 = 16'h2000; // Contoh: 0.25
    localparam signed [COEFF_WIDTH-1:0] H3 = 16'h1000; // Contoh: 0.125

    // Register untuk menunda input
    reg signed [DATA_WIDTH-1:0] data_reg [3:0]; // x(n), x(n-1), x(n-2), x(n-3)

    // Output dari setiap perkalian
    wire signed [DATA_WIDTH + COEFF_WIDTH -1:0] mul0_out;
    wire signed [DATA_WIDTH + COEFF_WIDTH -1:0] mul1_out;
    wire signed [DATA_WIDTH + COEFF_WIDTH -1:0] mul2_out;
    wire signed [DATA_WIDTH + COEFF_WIDTH -1:0] mul3_out;

    // Output dari penjumlahan
    wire signed [DATA_WIDTH + COEFF_WIDTH - COEFF_FRACTION_WIDTH:0] add0_out; // Sum of two products
    wire signed [DATA_WIDTH + COEFF_WIDTH - COEFF_FRACTION_WIDTH + 1:0] add1_out; // Sum of three products
    // o_data_sum akan menampung hasil akhir dari penjumlahan 4 produk

    // Register untuk validasi data output
    reg data_valid_reg;

    assign o_data_valid = data_valid_reg;

    // Penggeseran register input pada setiap tepi clock
    always @(posedge clk or posedge reset) begin
        if (reset) begin
            data_reg[0] <= 'd0;
            data_reg[1] <= 'd0;
            data_reg[2] <= 'd0;
            data_reg[3] <= 'd0;
            data_valid_reg <= 1'b0;
        end else begin
            data_reg[3] <= data_reg[2];
            data_reg[2] <= data_reg[1];
            data_reg[1] <= data_reg[0];
            data_reg[0] <= i_data;
            data_valid_reg <= 1'b1; // Data output valid setelah N tap delay terisi
        end
    end

    // Perkalian untuk setiap tap
    assign mul0_out = data_reg[0] * H0;
    assign mul1_out = data_reg[1] * H1;
    assign mul2_out = data_reg[2] * H2;
    assign mul3_out = data_reg[3] * H3;

    // Penjumlahan (struktur pohon penjumlah untuk Direct Form)
    // Perhatikan bahwa setiap penjumlahan dapat menambah 1 bit ke lebar data untuk menghindari overflow
    assign add0_out = (mul0_out >>> COEFF_FRACTION_WIDTH) + (mul1_out >>> COEFF_FRACTION_WIDTH);
    assign add1_out = add0_out + (mul2_out >>> COEFF_FRACTION_WIDTH);
    assign o_data_sum = add1_out + (mul3_out >>> COEFF_FRACTION_WIDTH);

endmodule


// cd D:\FIR_Filter
// iverilog -o fir_direct_form.vvp fir_4_tap_direct_form.v tb_fir_direct_form.v
// vvp fir_direct_form.vvp
// gtkwave fir_direct_form.vcd

tb_fir_direct_form.v
// tb_fir_direct_form.v
`timescale 1ns / 1ps

module tb_fir_direct_form;

    // Parameters
    parameter DATA_WIDTH = 16;
    parameter COEFF_WIDTH = 16;
    parameter COEFF_FRACTION_WIDTH = 15; // Q1.15 for coefficients

    // Signals
    reg clk;
    reg reset;
    reg signed [DATA_WIDTH-1:0] i_data;
    wire signed [DATA_WIDTH + COEFF_WIDTH - COEFF_FRACTION_WIDTH + 1:0] o_data_sum;
    wire o_data_valid;

    // Clock Generation
    always #5 clk = ~clk; // 10ns period (100 MHz)

    // DUT Instantiation
    fir_4_tap_direct_form #(
        .DATA_WIDTH(DATA_WIDTH),
        .COEFF_WIDTH(COEFF_WIDTH),
        .COEFF_FRACTION_WIDTH(COEFF_FRACTION_WIDTH)
    ) dut (
        .clk(clk),
        .reset(reset),
        .i_data(i_data),
        .o_data_sum(o_data_sum),
        .o_data_valid(o_data_valid)
    );

    // Initial Block
    initial begin
        // Initialize signals
        clk = 1'b0;
        reset = 1'b1;
        i_data = 'd0;

        // Dump waves for GTKWave
        $dumpfile("fir_direct_form.vcd");
        $dumpvars(0, tb_fir_direct_form);

        // Apply reset
        #10 reset = 1'b0;

        // Test vectors
        // Coefficients: h0=0.125, h1=0.25, h2=0.25, h3=0.125
        // Expected output formula: y(n) = round(h0*x(n) + h1*x(n-1) + h2*x(n-2) + h3*x(n-3))
        // Note: The shifting (>>> COEFF_FRACTION_WIDTH) effectively converts the fractional part to integer.
        // So, for 0.125 * 100 = 12.5, after shifting, it becomes 12.
        // The test data below is designed to produce easily verifiable integer outputs.

        // Example:
        // Assume x(n) = 8
        // h0*x(n) = 0.125 * 8 = 1.0
        // h1*x(n-1) = 0.25 * x(n-1)
        // h2*x(n-2) = 0.25 * x(n-2)
        // h3*x(n-3) = 0.125 * x(n-3)

        // y(n) = 1*x(n) + 2*x(n-1) + 2*x(n-2) + 1*x(n-3)  (after shifting, simplified example for integer coefficients)
        // With current fractional coefficients, we need to consider the rounding/truncation.

        // Let's use simple integer inputs to verify.
        // h0=0.125, h1=0.25, h2=0.25, h3=0.125
        // All coefficients are effectively (value * 2^15) in the module.
        // So a multiplication by H0 is actually data * 4096.
        // Then, the result is shifted right by 15. So, (data * 4096) / 2^15 = data * 0.125 (effectively).

        // Step 1: Input 100
        #10 i_data = 16'd100;
        // x(n)=100, x(n-1)=0, x(n-2)=0, x(n-3)=0
        // y(n) = 0.125*100 = 12.5 -> truncates to 12
        // o_data_sum should be 12 (after a few cycles for pipeline/register update)

        // Step 2: Input 200
        #10 i_data = 16'd200;
        // x(n)=200, x(n-1)=100, x(n-2)=0, x(n-3)=0
        // y(n) = 0.125*200 + 0.25*100 = 25 + 25 = 50

        // Step 3: Input 300
        #10 i_data = 16'd300;
        // x(n)=300, x(n-1)=200, x(n-2)=100, x(n-3)=0
        // y(n) = 0.125*300 + 0.25*200 + 0.25*100 = 37.5 + 50 + 25 = 112.5 -> truncates to 112

        // Step 4: Input 400
        #10 i_data = 16'd400;
        // x(n)=400, x(n-1)=300, x(n-2)=200, x(n-3)=100
        // y(n) = 0.125*400 + 0.25*300 + 0.25*200 + 0.125*100
        //      = 50 + 75 + 50 + 12.5 = 187.5 -> truncates to 187

        // Step 5: Input 0
        #10 i_data = 16'd0;
        // x(n)=0, x(n-1)=400, x(n-2)=300, x(n-3)=200
        // y(n) = 0.125*0 + 0.25*400 + 0.25*300 + 0.125*200
        //      = 0 + 100 + 75 + 25 = 200

        #50 $finish;
    end

    // Monitor outputs
    always @(posedge clk) begin
        if (o_data_valid) begin
            $display("Time: %0t, Input: %0d, Output: %0d", $time, i_data, o_data_sum);
        end
    end

endmodule

fir_direct_form.vcd
$date
	Mon Oct 20 10:16:23 2025
$end
$version
	Icarus Verilog
$end
$timescale
	1ps
$end
$scope module tb_fir_direct_form $end
$var wire 1 ! o_data_valid $end
$var wire 19 " o_data_sum [18:0] $end
$var parameter 32 # COEFF_FRACTION_WIDTH $end
$var parameter 32 $ COEFF_WIDTH $end
$var parameter 32 % DATA_WIDTH $end
$var reg 1 & clk $end
$var reg 16 ' i_data [15:0] $end
$var reg 1 ( reset $end
$scope module dut $end
$var wire 1 & clk $end
$var wire 16 ) i_data [15:0] $end
$var wire 1 ! o_data_valid $end
$var wire 1 ( reset $end
$var wire 19 * o_data_sum [18:0] $end
$var wire 32 + mul3_out [31:0] $end
$var wire 32 , mul2_out [31:0] $end
$var wire 32 - mul1_out [31:0] $end
$var wire 32 . mul0_out [31:0] $end
$var wire 19 / add1_out [18:0] $end
$var wire 18 0 add0_out [17:0] $end
$var parameter 32 1 COEFF_FRACTION_WIDTH $end
$var parameter 32 2 COEFF_WIDTH $end
$var parameter 32 3 DATA_WIDTH $end
$var parameter 16 4 H0 $end
$var parameter 16 5 H1 $end
$var parameter 16 6 H2 $end
$var parameter 16 7 H3 $end
$var reg 1 8 data_valid_reg $end
$upscope $end
$upscope $end
$enddefinitions $end
$comment Show the parameter values. $end
$dumpall
b1000000000000 7
b10000000000000 6
b10000000000000 5
b1000000000000 4
b10000 3
b10000 2
b1111 1
b10000 %
b10000 $
b1111 #
$end
#0
$dumpvars
08
b0 0
b0 /
b0 .
b0 -
b0 ,
b0 +
b0 *
b0 )
1(
b0 '
0&
b0 "
0!
$end
#5000
1&
#10000
0&
0(
#15000
1!
18
1&
#20000
0&
b1100100 '
b1100100 )
#25000
b1100 "
b1100 *
b1100 /
b1100 0
b1100100000000000000 .
1&
#30000
0&
b11001000 '
b11001000 )
#35000
b110010 "
b110010 *
b110010 /
b110010 0
b11001000000000000000 .
b11001000000000000000 -
1&
#40000
0&
b100101100 '
b100101100 )
#45000
b1110000 "
b1110000 *
b1010111 0
b1110000 /
b100101100000000000000 .
b110010000000000000000 -
b11001000000000000000 ,
1&
#50000
0&
b110010000 '
b110010000 )
#55000
b1111101 0
b10101111 /
b10111011 "
b10111011 *
b110010000000000000000 .
b1001011000000000000000 -
b110010000000000000000 ,
b1100100000000000000 +
1&
#60000
0&
b0 '
b0 )
#65000
b1100100 0
b10101111 /
b11001000 "
b11001000 *
b0 .
b1100100000000000000000 -
b1001011000000000000000 ,
b11001000000000000000 +
1&
#70000
0&
#75000
b0 0
b1100100 /
b10001001 "
b10001001 *
b0 -
b1100100000000000000000 ,
b100101100000000000000 +
1&
#80000
0&
#85000
b0 /
b110010 "
b110010 *
b0 ,
b110010000000000000000 +
1&
#90000
0&
#95000
b0 "
b0 *
b0 +
1&
